Metadata-Version: 2.1
Name: numpy-eiei
Version: 0.1.2
Summary: Equilibrated Input Embedding Initialization (EIEI)
Home-page: UNKNOWN
Author: Ulf Hamster
Author-email: 554c46@gmail.com
License: Apache License 2.0
Platform: UNKNOWN
Requires-Python: >=3.6
License-File: LICENSE
